<?xml version="1.0" encoding="utf-8" ?><dwsync><file name="code.php" server="ftp.diversitycomplete.com" local="3497368091" remote="319783739103079888" /><file name="get_all_leverage.php" server="ftp.diversitycomplete.com" local="3508883137" remote="16393774188" /><file name="get_all_media.php" server="ftp.diversitycomplete.com" local="3497368092" remote="319783739124247888" /><file name="get_all_trainings.php" server="ftp.diversitycomplete.com" local="3497368092" remote="319783739124247888" /><file name="get_leverage.php" server="ftp.diversitycomplete.com" local="3497368092" remote="319783739103252688" /><file name="get_media.php" server="ftp.diversitycomplete.com" local="3497368092" remote="319783739103252688" /><file name="get_reforms.php" server="ftp.diversitycomplete.com" local="3497368093" remote="319783739104030288" /><file name="get_reports.php" server="ftp.diversitycomplete.com" local="3497368093" remote="319783739133579028" /><file name="get_reports_admin1.php" server="ftp.diversitycomplete.com" local="3509752836" remote="16394644188" /><file name="get_trainings.php" server="ftp.diversitycomplete.com" local="3497368093" remote="319783739103079888" /><file name="get_users.php" server="ftp.diversitycomplete.com" local="3508944007" remote="16393835088" /><file name="sql_queries.php" server="ftp.diversitycomplete.com" local="3504201638" remote="16389096348" /></dwsync>