<?xml version="1.0" encoding="utf-8" ?><dwsync><file name="bootstrap-alert.js" server="ftp.diversitycomplete.com" local="3497368044" remote="319783739092625488" Dst="-1" /><file name="bootstrap-button.js" server="ftp.diversitycomplete.com" local="3497368046" remote="319783739092625488" Dst="-1" /><file name="bootstrap-carousel.js" server="ftp.diversitycomplete.com" local="3497368046" remote="319783739092625488" Dst="-1" /><file name="bootstrap-collapse.js" server="ftp.diversitycomplete.com" local="3497368046" remote="319783739092625488" Dst="-1" /><file name="bootstrap-popover.js" server="ftp.diversitycomplete.com" local="3497368049" remote="319783739092625488" Dst="-1" /><file name="bootstrap-dropdown.js" server="ftp.diversitycomplete.com" local="3497368049" remote="319783739092625488" Dst="-1" /><file name="bootstrap-modal.js" server="ftp.diversitycomplete.com" local="3497368049" remote="319783739092625488" Dst="-1" /><file name="bootstrap-tab.js" server="ftp.diversitycomplete.com" local="3497368051" remote="319783739092625488" Dst="-1" /><file name="bootstrap-scrollspy.js" server="ftp.diversitycomplete.com" local="3497368053" remote="319783739092625488" Dst="-1" /><file name="bootstrap-tooltip.js" server="ftp.diversitycomplete.com" local="3497368053" remote="319783739092625488" Dst="-1" /><file name="bootstrap-transition.js" server="ftp.diversitycomplete.com" local="3497368061" remote="319783739092625488" Dst="-1" /><file name="bootstrap-typeahead.js" server="ftp.diversitycomplete.com" local="3497368063" remote="319783739092625488" Dst="-1" /><file name="jquery.js" server="ftp.diversitycomplete.com" local="3497368065" remote="319783739092625488" Dst="-1" /></dwsync>